phidnet/__init__.py
phidnet/activation.py
phidnet/error.py
phidnet/feedforward.py
phidnet/gradient.py
phidnet/load.py
phidnet/loss.py
phidnet/model.py
phidnet/network_data.py
phidnet/one_hot_encode.py
phidnet/optimizer.py
phidnet/save.py
phidnet/set.py
phidnet/CNN/__init__.py
phidnet/CNN/affine.py
phidnet/CNN/backpropagation.py
phidnet/CNN/convolution.py
phidnet/CNN/feedforward.py
phidnet/CNN/layer.py
phidnet/CNN/model.py
phidnet/CNN/network_data.py
phidnet/CNN/optimizer.py
phidnet/CNN/pool.py
phidnet/CNN/preprocessing.py
phidnet/CNN/process.py
phidnet/CNN/set.py
phidnet/GUI/__init__.py
phidnet/GUI/graph.py
phidnet/RNN/__init__.py
phidnet/RNN/recurrent.py
phidnet/datasets/__init__.py
phidnet/datasets/mnist.py
phidnet/datasets/mnist_test.csv
phidnet/datasets/mnist_train.csv
phidnet/matrix/__init__.py
phidnet/matrix/matrix.py
phidnet/matrix/matrix_class.py
phidnet-0.1.2.dist-info/LICENSE
phidnet-0.1.2.dist-info/METADATA
phidnet-0.1.2.dist-info/WHEEL
phidnet-0.1.2.dist-info/top_level.txt
phidnet-0.1.2.dist-info/RECORD
